cylc/sphinx_ext/__init__.py
cylc/sphinx_ext/cylc_lang/__init__.py
cylc/sphinx_ext/cylc_lang/autodocumenters.py
cylc/sphinx_ext/cylc_lang/domains.py
cylc/sphinx_ext/cylc_lang/lexers.py
cylc/sphinx_ext/cylc_lang/tests/test_autodocumenters.py
cylc/sphinx_ext/diff_selection/__init__.py
cylc/sphinx_ext/diff_selection/_static/css/diff_selector.css
cylc/sphinx_ext/diff_selection/_static/js/diff_selector.js
cylc/sphinx_ext/grid_table/__init__.py
cylc/sphinx_ext/grid_table/_static/css/grid_table.css
cylc/sphinx_ext/hieroglyph_addons/__init__.py
cylc/sphinx_ext/hieroglyph_addons/_static/css/hieroglyph_theme_addons.css
cylc/sphinx_ext/literal_sub_include/__init__.py
cylc/sphinx_ext/literal_sub_include/directives.py
cylc/sphinx_ext/minicylc/__init__.py
cylc/sphinx_ext/minicylc/minicylc.py
cylc/sphinx_ext/minicylc/_static/js/minicylc.js
cylc/sphinx_ext/practical/__init__.py
cylc/sphinx_ext/practical/admonitions.py
cylc/sphinx_ext/practical/_static/css/tutorial.css
cylc/sphinx_ext/practical/_static/js/spoiler.js
cylc/sphinx_ext/rst_example/__init__.py
cylc/sphinx_ext/rst_example/directives.py
cylc/sphinx_ext/rtd_theme_addons/__init__.py
cylc/sphinx_ext/rtd_theme_addons/_static/css/addons.css
cylc/sphinx_ext/rtd_theme_addons/_static/js/addons.js
cylc/sphinx_ext/sub_lang/__init__.py
cylc/sphinx_ext/sub_lang/lexer.py
cylc_sphinx_extensions-1.4.3.dist-info/LICENSE
cylc_sphinx_extensions-1.4.3.dist-info/METADATA
cylc_sphinx_extensions-1.4.3.dist-info/WHEEL
cylc_sphinx_extensions-1.4.3.dist-info/top_level.txt
cylc_sphinx_extensions-1.4.3.dist-info/RECORD
