Metadata-Version: 2.1
Name: cylc-sphinx-extensions
Version: 1.4.3
Summary: Sphinx extensions for documenting Cylc
Home-page: UNKNOWN
License: GPL
Platform: UNKNOWN
Requires-Dist: sphinx >=2.1
Provides-Extra: all
Requires-Dist: hieroglyph ; extra == 'all'
Requires-Dist: pytest ; extra == 'all'
Requires-Dist: pygments ; extra == 'all'
Requires-Dist: sphinx-rtd-theme ; extra == 'all'
Requires-Dist: cylc-flow ; extra == 'all'
Requires-Dist: pycodestyle ; extra == 'all'
Provides-Extra: cylc_lang
Requires-Dist: pygments ; extra == 'cylc_lang'
Requires-Dist: cylc-flow ; extra == 'cylc_lang'
Provides-Extra: hieroglyph_addons
Requires-Dist: hieroglyph ; extra == 'hieroglyph_addons'
Provides-Extra: rtd_theme_addons
Requires-Dist: sphinx-rtd-theme ; extra == 'rtd_theme_addons'
Provides-Extra: sub_lang
Requires-Dist: pygments ; extra == 'sub_lang'
Provides-Extra: test
Requires-Dist: pycodestyle ; extra == 'test'
